LASER.v
`timescale 1ns/10ps

module LASER (
input CLK,
input RST,
input [3:0] X,
input [3:0] Y,
output reg [3:0] C1X,
output reg [3:0] C1Y,
output reg [3:0] C2X,
output reg [3:0] C2Y,
output reg DONE);

always @(posedge CLK or posedge RST) begin
    if (RST) begin
        C1X <= 4'd0;
        C1Y <= 4'd0;
        C2X <= 4'd0;
        C2Y <= 4'd0;
        DONE <= 1'b0;
    end
    else begin
        C1X <= 4'd4;
        C1Y <= 4'd10;
        C2X <= 4'd11;
        C2Y <= 4'd12;
        DONE <= 1'b0;  
    end
end

endmodule

tb.v
`timescale 1ns/10ps
`define CYCLE      8.0  
`define SDFFILE    "./LASER_syn.sdf"
`define MAX_CYCLE_PER_PATTERN  500
//`define USECOLOR 
`define P1

module testfixture();

parameter PAT_NUMBER = 1;
parameter PIXELS_PER_PAT = 40;
parameter IMG_SIZE = 16;
parameter PAT_STR_LEN = 32;

localparam [7:0] CHAR_MINUS    = "-";
localparam [7:0] CHAR_STAR     = "*";
localparam [7:0] CHAR_LOWER_X  = "x";
localparam [7:0] CHAR_UPPER_X  = "X";
localparam [7:0] CHAR_PLUS     = "+";

function integer pixel_index;
    input integer pat_idx;
    input integer pix_idx;
    integer limited_pix;
    integer limited_pat;
begin
    limited_pix = pix_idx;
    if (limited_pix < 0)
        limited_pix = 0;
    else if (limited_pix >= PIXELS_PER_PAT)
        limited_pix = PIXELS_PER_PAT - 1;

    limited_pat = pat_idx;
    if (limited_pat < 0)
        limited_pat = 0;
    else if (limited_pat >= PAT_NUMBER)
        limited_pat = PAT_NUMBER - 1;

    pixel_index = limited_pat * PIXELS_PER_PAT + limited_pix;
end
endfunction

integer fd;

reg CLK;
reg RST;
wire [3:0] X;
wire [3:0] Y;
wire [3:0] C1X;
wire [3:0] C1Y;
wire [3:0] C2X;
wire [3:0] C2Y;
wire DONE;

LASER u_LASER(
.CLK(CLK),
.RST(RST),
.X(X),
.Y(Y),
.C1X(C1X),
.C1Y(C1Y),
.C2X(C2X),
.C2Y(C2Y),
.DONE(DONE));

`ifdef SDF
    initial $sdf_annotate(`SDFFILE, u_LASER);
`endif

always begin
    #(`CYCLE/2) CLK = ~CLK;
end

parameter ST_RESET = 0;
parameter ST_PATTERN = 1;
parameter ST_RUN = 2;
parameter ST_RETURN = 3;

reg [1:0] state;
reg [1:0] rst_count;
reg [5:0] pixel_count;
integer pat_n;
reg [30:0] cycle_pat;
reg [30:0] cycle_total;

integer i;
integer j;
integer items_read;
integer pixel_slot;

integer optmax [0:PAT_NUMBER-1];
integer PX [0:PAT_NUMBER*PIXELS_PER_PAT-1];
integer PY [0:PAT_NUMBER*PIXELS_PER_PAT-1];
integer RET_C1X [0:PAT_NUMBER-1];
integer RET_C1Y [0:PAT_NUMBER-1];
integer RET_C2X [0:PAT_NUMBER-1];
integer RET_C2Y [0:PAT_NUMBER-1];
reg [PAT_STR_LEN*8-1:0] pattern_files [0:PAT_NUMBER-1];

integer cover_sum;
integer total_cover_sum;
integer optimum_sum;
integer d1;
integer d2;
integer wait_done;

reg [7:0] img_mem [0:IMG_SIZE*IMG_SIZE-1];

wire [31:0] current_px_value;
wire [31:0] current_py_value;

assign current_px_value = PX[pixel_index(pat_n, pixel_count)];
assign current_py_value = PY[pixel_index(pat_n, pixel_count)];
assign X = current_px_value[3:0];
assign Y = current_py_value[3:0];

initial begin
    CLK = 1'b0;
    RST = 1'b0;
    state = ST_RESET;
    rst_count = 2'b00;
    pixel_count = 6'b0;
    pat_n = 0;
    cycle_pat = 0;
    cycle_total = 0;
    wait_done = 0;
    total_cover_sum = 0;
    optimum_sum = 0;
end

initial begin
`ifdef P2
    pattern_files[0] = "img2.pattern";
`elsif P3
    pattern_files[0] = "img3.pattern";
`elsif P4
    pattern_files[0] = "img4.pattern";
`elsif P5
    pattern_files[0] = "img5.pattern";
`elsif P6
    pattern_files[0] = "img6.pattern";
`else
    pattern_files[0] = "img1.pattern";
`endif

    for (i = 0; i < PAT_NUMBER; i = i + 1) begin
        optmax[i] = 0;
        RET_C1X[i] = 0;
        RET_C1Y[i] = 0;
        RET_C2X[i] = 0;
        RET_C2Y[i] = 0;

        for (j = 0; j < PIXELS_PER_PAT; j = j + 1) begin
            pixel_slot = i * PIXELS_PER_PAT + j;
            PX[pixel_slot] = 0;
            PY[pixel_slot] = 0;
        end

        fd = $fopen(pattern_files[i], "r");
        if (fd == 0) begin
            $display("Failed open %s", pattern_files[i]);
            $finish;
        end

        items_read = $fscanf(fd, "optimum=%d\n", optmax[i]);
        if (items_read != 1) begin
            $display("Pattern %0d header format error", i + 1);
            $finish;
        end

        for (j = 0; j < PIXELS_PER_PAT; j = j + 1) begin
            pixel_slot = i * PIXELS_PER_PAT + j;
            items_read = $fscanf(fd, "%d %d\n", PX[pixel_slot], PY[pixel_slot]);
            if (items_read != 2) begin
                $display("Pattern %0d data format error at entry %0d", i + 1, j);
                $finish;
            end
        end

        $fclose(fd);
    end
end

always @(posedge CLK) begin
    cycle_total <= cycle_total + 1;
end

always @(posedge CLK) begin
    case (state)
        ST_RESET: begin
            if (rst_count == 2) begin
                #1 RST <= 1'b0;
                rst_count <= 0;
                state <= ST_PATTERN;
            end else begin
                #1 RST <= 1'b1;
                rst_count <= rst_count + 1;
                pixel_count <= 0;
                wait_done <= 0;
            end
        end
        ST_PATTERN: begin
            if (DONE == 0) begin
                if (pixel_count < PIXELS_PER_PAT) begin
                    #1;
                    pixel_count <= pixel_count + 1;
                end else begin
                    state <= ST_RUN;
                    cycle_pat <= 0;
                end
            end else begin
                if (pixel_count == 0) begin
                    if (DONE === 1'bx) begin
                        $display("\n%10t , ERROR, DONE is in unknown state. Simlation terminated\n", $time);
                        $finish;
                    end else begin
                        #1;
                        $display("%10t , please pull down signal DONE", $time);
                        wait_done <= wait_done + 1;
                        if (wait_done > 10) begin
                            $display("\n%t , ERROR, please pull down signal DONE. Simlation terminated\n", $time);
                            $finish;
                        end
                    end
                end else begin
                    $display("\n%10t, ERROR, received DONE while send pattern, %s %3d pixel. Simlation terminated\n",
                             $time, pattern_files[pat_n], pixel_count);
                    $finish;
                end
            end
        end
        ST_RUN: begin
            if (DONE == 0) begin
                cycle_pat <= cycle_pat + 1;
                if (cycle_pat > `MAX_CYCLE_PER_PATTERN) begin
                    $display("== PATTERN %s", pattern_files[pat_n]);
                    $display("-- Max cycle pre pattern reached, force output result C1(%2d,%2d),C2(%2d,%2d)",
                             C1X, C1Y, C2X, C2Y);
                    count_cover(C1X, C1Y, C2X, C2Y, cover_sum, total_cover_sum, optimum_sum);
                    if (PAT_NUMBER == 1) begin
                        draw_img(C1X, C1Y, C2X, C2Y, pat_n);
                    end
                    RET_C1X[pat_n] <= C1X;
                    RET_C1Y[pat_n] <= C1Y;
                    RET_C2X[pat_n] <= C2X;
                    RET_C2Y[pat_n] <= C2Y;
                    if (pat_n < PAT_NUMBER - 1) begin
                        pat_n <= pat_n + 1;
                        pixel_count <= 0;
                        rst_count <= 0;
                        state <= ST_RESET;
                    end else begin
                        $display ("");
                        $display ("*******************************");
                        $display ("**   Finish Simulation       **");
                        $display ("**   RUN CYCLE = %10d  **", cycle_total);
                        $display ("**   Cover total = %3d/%3d   **", total_cover_sum, optimum_sum);
                        $display ("*******************************");
                        $finish;
                    end
                end
            end else begin
                $display("== PATTERN %s", pattern_files[pat_n]);
                $display("---- Used Cycle: %10d", cycle_pat);
                $display("---- Get Return: C1(%2d,%2d),C2(%2d,%2d)", C1X, C1Y, C2X, C2Y);
                count_cover(C1X, C1Y, C2X, C2Y, cover_sum, total_cover_sum, optimum_sum);
                if (PAT_NUMBER == 1) begin
                    draw_img(C1X, C1Y, C2X, C2Y, pat_n);
                end
                RET_C1X[pat_n] <= C1X;
                RET_C1Y[pat_n] <= C1Y;
                RET_C2X[pat_n] <= C2X;
                RET_C2Y[pat_n] <= C2Y;

                if (pat_n < PAT_NUMBER - 1) begin
                    pat_n <= pat_n + 1;
                    pixel_count <= 0;
                    state <= ST_PATTERN;
                end else begin
                    $display ("");
                    $display ("*******************************");
                    $display ("**   Finish Simulation       **");
                    $display ("**   RUN CYCLE = %10d  **", cycle_total);
                    $display ("**   Cover total = %3d/%3d   **", total_cover_sum, optimum_sum);
                    $display ("*******************************");
                    $finish;
                end
            end
        end
        default: begin
        end
    endcase
end

initial begin
    $display("*******************************");
    $display("** Simulation Start          **");
    $display("*******************************");
end

initial begin
    $dumpfile("laser.vcd");
    $dumpvars();
end

task count_cover;
    input [3:0] C1X;
    input [3:0] C1Y;
    input [3:0] C2X;
    input [3:0] C2Y;
    output integer cover_sum;
    inout integer total_cover_sum;
    inout integer optimum_sum;
    integer sample_idx;
    integer px_value;
    integer py_value;
    integer c1x_int;
    integer c1y_int;
    integer c2x_int;
    integer c2y_int;
begin
    cover_sum = 0;
    c1x_int = C1X;
    c1y_int = C1Y;
    c2x_int = C2X;
    c2y_int = C2Y;
    for (i = 0; i < PIXELS_PER_PAT; i = i + 1) begin
        sample_idx = pixel_index(pat_n, i);
        px_value = PX[sample_idx];
        py_value = PY[sample_idx];

        if ((^C1X === 1'bx) || (^C1Y === 1'bx)) begin
            d1 = 100;
        end else begin
            d1 = (c1x_int - px_value) * (c1x_int - px_value) +
                 (c1y_int - py_value) * (c1y_int - py_value);
        end

        if ((^C2X === 1'bx) || (^C2Y === 1'bx)) begin
            d2 = 100;
        end else begin
            d2 = (c2x_int - px_value) * (c2x_int - px_value) +
                 (c2y_int - py_value) * (c2y_int - py_value);
        end

        if ((d1 <= 16) || (d2 <= 16)) begin
            cover_sum = cover_sum + 1;
        end
    end
    total_cover_sum = total_cover_sum + cover_sum;
    optimum_sum = optimum_sum + optmax[pat_n];
    $display("---- cover = %3d, optimum = %3d", cover_sum, optmax[pat_n]);
end
endtask

task draw_img;
    input [3:0] C1X;
    input [3:0] C1Y;
    input [3:0] C2X;
    input [3:0] C2Y;
    input integer pat_idx;
    integer img_idx;
    integer px_value;
    integer py_value;
    integer c1x_int;
    integer c1y_int;
    integer c2x_int;
    integer c2y_int;
begin
    c1x_int = C1X;
    c1y_int = C1Y;
    c2x_int = C2X;
    c2y_int = C2Y;

    for (j = 0; j < IMG_SIZE; j = j + 1) begin
        for (i = 0; i < IMG_SIZE; i = i + 1) begin
            img_idx = i * IMG_SIZE + j;
            img_mem[img_idx] = CHAR_MINUS;
        end
    end

    if ((c1x_int < IMG_SIZE) && (c1y_int < IMG_SIZE)) begin
        img_mem[c1x_int * IMG_SIZE + c1y_int] = CHAR_STAR;
    end
    if ((c2x_int < IMG_SIZE) && (c2y_int < IMG_SIZE)) begin
        img_mem[c2x_int * IMG_SIZE + c2y_int] = CHAR_STAR;
    end

    for (i = 0; i < PIXELS_PER_PAT; i = i + 1) begin
        px_value = PX[pixel_index(pat_idx, i)];
        py_value = PY[pixel_index(pat_idx, i)];

        if ((^C1X === 1'bx) || (^C1Y === 1'bx)) begin
            d1 = 100;
        end else begin
            d1 = (c1x_int - px_value) * (c1x_int - px_value) +
                 (c1y_int - py_value) * (c1y_int - py_value);
        end

        if ((^C2X === 1'bx) || (^C2Y === 1'bx)) begin
            d2 = 100;
        end else begin
            d2 = (c2x_int - px_value) * (c2x_int - px_value) +
                 (c2y_int - py_value) * (c2y_int - py_value);
        end

        if ((px_value < IMG_SIZE) && (py_value < IMG_SIZE)) begin
            img_idx = px_value * IMG_SIZE + py_value;
            if ((d1 <= 16) || (d2 <= 16)) begin
                img_mem[img_idx] = CHAR_LOWER_X;
                if ((px_value == c1x_int) && (py_value == c1y_int)) begin
                    img_mem[img_idx] = CHAR_UPPER_X;
                end
                if ((px_value == c2x_int) && (py_value == c2y_int)) begin
                    img_mem[img_idx] = CHAR_UPPER_X;
                end
            end else begin
                img_mem[img_idx] = CHAR_PLUS;
            end
        end
    end

    $display("   0 1 2 3 4 5 6 7 8 9 a b c d e f");
    for (j = 0; j < IMG_SIZE; j = j + 1) begin
        $write(" %1x", j[3:0]);
        for (i = 0; i < IMG_SIZE; i = i + 1) begin
            img_idx = i * IMG_SIZE + j;
`ifdef USECOLOR
            case (img_mem[img_idx])
                CHAR_PLUS: begin
                    $write("%c[1;34m", 27);
                    $write("%s", {" ", img_mem[img_idx]});
                    $write("%c[0m", 27);
                end
                CHAR_LOWER_X: begin
                    $write("%c[1;31m", 27);
                    $write("%s", {" ", img_mem[img_idx]});
                    $write("%c[0m", 27);
                end
                CHAR_STAR,
                CHAR_UPPER_X: begin
                    $write("%c[1;32m", 27);
                    $write("%s", {" ", img_mem[img_idx]});
                    $write("%c[0m", 27);
                end
                default: begin
                    $write("%s", {" ", img_mem[img_idx]});
                end
            endcase
`else
            $write("%s", {" ", img_mem[img_idx]});
`endif
        end
        $write("\n");
    end
end
endtask

endmodule

laser.vcd
$date
	Tue Nov  4 03:29:08 2025
$end
$version
	Icarus Verilog
$end
$timescale
	10ps
$end
$scope module testfixture $end
$var wire 32 ! current_px_value [31:0] $end
$var wire 32 " current_py_value [31:0] $end
$var wire 4 # Y [3:0] $end
$var wire 4 $ X [3:0] $end
$var wire 1 % DONE $end
$var wire 4 & C2Y [3:0] $end
$var wire 4 ' C2X [3:0] $end
$var wire 4 ( C1Y [3:0] $end
$var wire 4 ) C1X [3:0] $end
$var parameter 8 * CHAR_LOWER_X $end
$var parameter 8 + CHAR_MINUS $end
$var parameter 8 , CHAR_PLUS $end
$var parameter 8 - CHAR_STAR $end
$var parameter 8 . CHAR_UPPER_X $end
$var parameter 32 / IMG_SIZE $end
$var parameter 32 0 PAT_NUMBER $end
$var parameter 32 1 PAT_STR_LEN $end
$var parameter 32 2 PIXELS_PER_PAT $end
$var parameter 32 3 ST_PATTERN $end
$var parameter 32 4 ST_RESET $end
$var parameter 32 5 ST_RETURN $end
$var parameter 32 6 ST_RUN $end
$var reg 1 7 CLK $end
$var reg 1 8 RST $end
$var reg 31 9 cycle_pat [30:0] $end
$var reg 31 : cycle_total [30:0] $end
$var reg 6 ; pixel_count [5:0] $end
$var reg 2 < rst_count [1:0] $end
$var reg 2 = state [1:0] $end
$var integer 32 > cover_sum [31:0] $end
$var integer 32 ? d1 [31:0] $end
$var integer 32 @ d2 [31:0] $end
$var integer 32 A fd [31:0] $end
$var integer 32 B i [31:0] $end
$var integer 32 C items_read [31:0] $end
$var integer 32 D j [31:0] $end
$var integer 32 E optimum_sum [31:0] $end
$var integer 32 F pat_n [31:0] $end
$var integer 32 G pixel_slot [31:0] $end
$var integer 32 H total_cover_sum [31:0] $end
$var integer 32 I wait_done [31:0] $end
$scope function pixel_index $end
$var integer 32 J limited_pat [31:0] $end
$var integer 32 K limited_pix [31:0] $end
$var integer 32 L pat_idx [31:0] $end
$var integer 32 M pix_idx [31:0] $end
$upscope $end
$scope module u_LASER $end
$var wire 1 7 CLK $end
$var wire 1 8 RST $end
$var wire 4 N X [3:0] $end
$var wire 4 O Y [3:0] $end
$var reg 4 P C1X [3:0] $end
$var reg 4 Q C1Y [3:0] $end
$var reg 4 R C2X [3:0] $end
$var reg 4 S C2Y [3:0] $end
$var reg 1 % DONE $end
$upscope $end
$scope task count_cover $end
$var reg 4 T C1X [3:0] $end
$var reg 4 U C1Y [3:0] $end
$var reg 4 V C2X [3:0] $end
$var reg 4 W C2Y [3:0] $end
$var integer 32 X c1x_int [31:0] $end
$var integer 32 Y c1y_int [31:0] $end
$var integer 32 Z c2x_int [31:0] $end
$var integer 32 [ c2y_int [31:0] $end
$var integer 32 \ cover_sum [31:0] $end
$var integer 32 ] optimum_sum [31:0] $end
$var integer 32 ^ px_value [31:0] $end
$var integer 32 _ py_value [31:0] $end
$var integer 32 ` sample_idx [31:0] $end
$var integer 32 a total_cover_sum [31:0] $end
$upscope $end
$scope task draw_img $end
$var reg 4 b C1X [3:0] $end
$var reg 4 c C1Y [3:0] $end
$var reg 4 d C2X [3:0] $end
$var reg 4 e C2Y [3:0] $end
$var integer 32 f c1x_int [31:0] $end
$var integer 32 g c1y_int [31:0] $end
$var integer 32 h c2x_int [31:0] $end
$var integer 32 i c2y_int [31:0] $end
$var integer 32 j img_idx [31:0] $end
$var integer 32 k pat_idx [31:0] $end
$var integer 32 l px_value [31:0] $end
$var integer 32 m py_value [31:0] $end
$upscope $end
$upscope $end
$enddefinitions $end
$comment Show the parameter values. $end
$dumpall
b10 6
b11 5
b0 4
b1 3
b101000 2
b100000 1
b1 0
b10000 /
b1011000 .
b101010 -
b101011 ,
b101101 +
b1111000 *
$end
#0
$dumpvars
bx m
bx l
bx k
bx j
bx i
bx h
bx g
bx f
bx e
bx d
bx c
bx b
bx a
bx `
bx _
bx ^
bx ]
bx \
bx [
bx Z
bx Y
bx X
bx W
bx V
bx U
bx T
bx S
bx R
bx Q
bx P
b0 O
b1011 N
b0 M
b0 L
b0 K
b0 J
b0 I
b0 H
b100111 G
b0 F
b0 E
b101000 D
b10 C
b1 B
b10000000000000000000000000000011 A
bx @
bx ?
bx >
b0 =
b0 <
b0 ;
b0 :
b0 9
08
07
bx )
bx (
bx '
bx &
x%
b1011 $
b0 #
b0 "
b1011 !
$end
#400
0%
b1100 &
b1100 S
b1011 '
b1011 R
b1010 (
b1010 Q
b100 )
b100 P
b1 :
17
#500
b0 &
b0 S
b0 '
b0 R
b0 (
b0 Q
b0 )
b0 P
b1 <
18
#800
07
#1200
b10 :
17
#1300
b10 <
#1600
07
#2000
b11 :
17
#2100
b1 =
b0 <
08
#2400
07
#2800
b1100 &
b1100 S
b1011 '
b1011 R
b1010 (
b1010 Q
b100 )
b100 P
b100 :
17
#2900
b10 $
b10 N
b1 #
b1 O
b10 !
b1 "
b1 K
b1 M
b1 ;
#3200
07
#3600
b101 :
17
#3700
b1000 $
b1000 N
b1000 !
b10 K
b10 M
b10 ;
#4000
07
#4400
b110 :
17
#4500
b1010 $
b1010 N
b1010 !
b11 K
b11 M
b11 ;
#4800
07
#5200
b111 :
17
#5300
b100 $
b100 N
b110 #
b110 O
b100 !
b110 "
b100 K
b100 M
b100 ;
#5600
07
#6000
b1000 :
17
#6100
b1 $
b1 N
b111 #
b111 O
b1 !
b111 "
b101 K
b101 M
b101 ;
#6400
07
#6800
b1001 :
17
#6900
b10 $
b10 N
b10 !
b110 K
b110 M
b110 ;
#7200
07
#7600
b1010 :
17
#7700
b111 $
b111 N
b111 !
b111 K
b111 M
b111 ;
#8000
07
#8400
b1011 :
17
#8500
b1000 $
b1000 N
b1000 !
b1000 K
b1000 M
b1000 ;
#8800
07
#9200
b1100 :
17
#9300
b1001 $
b1001 N
b1001 !
b1001 K
b1001 M
b1001 ;
#9600
07
#10000
b1101 :
17
#10100
b1101 $
b1101 N
b1101 !
b1010 K
b1010 M
b1010 ;
#10400
07
#10800
b1110 :
17
#10900
b101 $
b101 N
b1000 #
b1000 O
b101 !
b1000 "
b1011 K
b1011 M
b1011 ;
#11200
07
#11600
b1111 :
17
#11700
b111 $
b111 N
b111 !
b1100 K
b1100 M
b1100 ;
#12000
07
#12400
b10000 :
17
#12500
b100 $
b100 N
b1001 #
b1001 O
b100 !
b1001 "
b1101 K
b1101 M
b1101 ;
#12800
07
#13200
b10001 :
17
#13300
b110 $
b110 N
b110 !
b1110 K
b1110 M
b1110 ;
#13600
07
#14000
b10010 :
17
#14100
b1010 $
b1010 N
b1010 !
b1111 K
b1111 M
b1111 ;
#14400
07
#14800
b10011 :
17
#14900
b1100 $
b1100 N
b1100 !
b10000 K
b10000 M
b10000 ;
#15200
07
#15600
b10100 :
17
#15700
b11 $
b11 N
b1010 #
b1010 O
b11 !
b1010 "
b10001 K
b10001 M
b10001 ;
#16000
07
#16400
b10101 :
17
#16500
b111 $
b111 N
b111 !
b10010 K
b10010 M
b10010 ;
#16800
07
#17200
b10110 :
17
#17300
b1000 $
b1000 N
b1000 !
b10011 K
b10011 M
b10011 ;
#17600
07
#18000
b10111 :
17
#18100
b1101 $
b1101 N
b1101 !
b10100 K
b10100 M
b10100 ;
#18400
07
#18800
b11000 :
17
#18900
b1110 $
b1110 N
b1110 !
b10101 K
b10101 M
b10101 ;
#19200
07
#19600
b11001 :
17
#19700
b11 $
b11 N
b1011 #
b1011 O
b11 !
b1011 "
b10110 K
b10110 M
b10110 ;
#20000
07
#20400
b11010 :
17
#20500
b111 $
b111 N
b111 !
b10111 K
b10111 M
b10111 ;
#20800
07
#21200
b11011 :
17
#21300
b1000 $
b1000 N
b1000 !
b11000 K
b11000 M
b11000 ;
#21600
07
#22000
b11100 :
17
#22100
b1011 $
b1011 N
b1011 !
b11001 K
b11001 M
b11001 ;
#22400
07
#22800
b11101 :
17
#22900
b1100 $
b1100 N
b1100 !
b11010 K
b11010 M
b11010 ;
#23200
07
#23600
b11110 :
17
#23700
b1 $
b1 N
b1100 #
b1100 O
b1 !
b1100 "
b11011 K
b11011 M
b11011 ;
#24000
07
#24400
b11111 :
17
#24500
b101 $
b101 N
b101 !
b11100 K
b11100 M
b11100 ;
#24800
07
#25200
b100000 :
17
#25300
b1000 $
b1000 N
b1000 !
b11101 K
b11101 M
b11101 ;
#25600
07
#26000
b100001 :
17
#26100
b1011 $
b1011 N
b1011 !
b11110 K
b11110 M
b11110 ;
#26400
07
#26800
b100010 :
17
#26900
b1101 $
b1101 N
b1101 !
b11111 K
b11111 M
b11111 ;
#27200
07
#27600
b100011 :
17
#27700
b1110 $
b1110 N
b1110 !
b100000 K
b100000 M
b100000 ;
#28000
07
#28400
b100100 :
17
#28500
b11 $
b11 N
b1101 #
b1101 O
b11 !
b1101 "
b100001 K
b100001 M
b100001 ;
#28800
07
#29200
b100101 :
17
#29300
b100 $
b100 N
b100 !
b100010 K
b100010 M
b100010 ;
#29600
07
#30000
b100110 :
17
#30100
b1101 $
b1101 N
b1101 !
b100011 K
b100011 M
b100011 ;
#30400
07
#30800
b100111 :
17
#30900
b1001 $
b1001 N
b1110 #
b1110 O
b1001 !
b1110 "
b100100 K
b100100 M
b100100 ;
#31200
07
#31600
b101000 :
17
#31700
b1011 $
b1011 N
b1011 !
b100101 K
b100101 M
b100101 ;
#32000
07
#32400
b101001 :
17
#32500
b1101 $
b1101 N
b1101 !
b100110 K
b100110 M
b100110 ;
#32800
07
#33200
b101010 :
17
#33300
b110 $
b110 N
b1111 #
b1111 O
b110 !
b1111 "
b100111 K
b100111 M
b100111 ;
#33600
07
#34000
b101011 :
17
#34100
b100111 K
b101000 M
b101000 ;
#34400
07
#34800
b101100 :
b10 =
17
#35200
07
#35600
b1 9
b101101 :
17
#36000
07
#36400
b101110 :
b10 9
17
#36800
07
#37200
b11 9
b101111 :
17
#37600
07
#38000
b110000 :
b100 9
17
#38400
07
#38800
b101 9
b110001 :
17
#39200
07
#39600
b110010 :
b110 9
17
#40000
07
#40400
b111 9
b110011 :
17
#40800
07
#41200
b110100 :
b1000 9
17
#41600
07
#42000
b1001 9
b110101 :
17
#42400
07
#42800
b110110 :
b1010 9
17
#43200
07
#43600
b1011 9
b110111 :
17
#44000
07
#44400
b111000 :
b1100 9
17
#44800
07
#45200
b1101 9
b111001 :
17
#45600
07
#46000
b111010 :
b1110 9
17
#46400
07
#46800
b1111 9
b111011 :
17
#47200
07
#47600
b111100 :
b10000 9
17
#48000
07
#48400
b10001 9
b111101 :
17
#48800
07
#49200
b111110 :
b10010 9
17
#49600
07
#50000
b10011 9
b111111 :
17
#50400
07
#50800
b1000000 :
b10100 9
17
#51200
07
#51600
b10101 9
b1000001 :
17
#52000
07
#52400
b1000010 :
b10110 9
17
#52800
07
#53200
b10111 9
b1000011 :
17
#53600
07
#54000
b1000100 :
b11000 9
17
#54400
07
#54800
b11001 9
b1000101 :
17
#55200
07
#55600
b1000110 :
b11010 9
17
#56000
07
#56400
b11011 9
b1000111 :
17
#56800
07
#57200
b1001000 :
b11100 9
17
#57600
07
#58000
b11101 9
b1001001 :
17
#58400
07
#58800
b1001010 :
b11110 9
17
#59200
07
#59600
b11111 9
b1001011 :
17
#60000
07
#60400
b1001100 :
b100000 9
17
#60800
07
#61200
b100001 9
b1001101 :
17
#61600
07
#62000
b1001110 :
b100010 9
17
#62400
07
#62800
b100011 9
b1001111 :
17
#63200
07
#63600
b1010000 :
b100100 9
17
#64000
07
#64400
b100101 9
b1010001 :
17
#64800
07
#65200
b1010010 :
b100110 9
17
#65600
07
#66000
b100111 9
b1010011 :
17
#66400
07
#66800
b1010100 :
b101000 9
17
#67200
07
#67600
b101001 9
b1010101 :
17
#68000
07
#68400
b1010110 :
b101010 9
17
#68800
07
#69200
b101011 9
b1010111 :
17
#69600
07
#70000
b1011000 :
b101100 9
17
#70400
07
#70800
b101101 9
b1011001 :
17
#71200
07
#71600
b1011010 :
b101110 9
17
#72000
07
#72400
b101111 9
b1011011 :
17
#72800
07
#73200
b1011100 :
b110000 9
17
#73600
07
#74000
b110001 9
b1011101 :
17
#74400
07
#74800
b1011110 :
b110010 9
17
#75200
07
#75600
b110011 9
b1011111 :
17
#76000
07
#76400
b1100000 :
b110100 9
17
#76800
07
#77200
b110101 9
b1100001 :
17
#77600
07
#78000
b1100010 :
b110110 9
17
#78400
07
#78800
b110111 9
b1100011 :
17
#79200
07
#79600
b1100100 :
b111000 9
17
#80000
07
#80400
b111001 9
b1100101 :
17
#80800
07
#81200
b1100110 :
b111010 9
17
#81600
07
#82000
b111011 9
b1100111 :
17
#82400
07
#82800
b1101000 :
b111100 9
17
#83200
07
#83600
b111101 9
b1101001 :
17
#84000
07
#84400
b1101010 :
b111110 9
17
#84800
07
#85200
b111111 9
b1101011 :
17
#85600
07
#86000
b1101100 :
b1000000 9
17
#86400
07
#86800
b1000001 9
b1101101 :
17
#87200
07
#87600
b1101110 :
b1000010 9
17
#88000
07
#88400
b1000011 9
b1101111 :
17
#88800
07
#89200
b1110000 :
b1000100 9
17
#89600
07
#90000
b1000101 9
b1110001 :
17
#90400
07
#90800
b1110010 :
b1000110 9
17
#91200
07
#91600
b1000111 9
b1110011 :
17
#92000
07
#92400
b1110100 :
b1001000 9
17
#92800
07
#93200
b1001001 9
b1110101 :
17
#93600
07
#94000
b1110110 :
b1001010 9
17
#94400
07
#94800
b1001011 9
b1110111 :
17
#95200
07
#95600
b1111000 :
b1001100 9
17
#96000
07
#96400
b1001101 9
b1111001 :
17
#96800
07
#97200
b1111010 :
b1001110 9
17
#97600
07
#98000
b1001111 9
b1111011 :
17
#98400
07
#98800
b1111100 :
b1010000 9
17
#99200
07
#99600
b1010001 9
b1111101 :
17
#100000
07
#100400
b1111110 :
b1010010 9
17
#100800
07
#101200
b1010011 9
b1111111 :
17
#101600
07
#102000
b10000000 :
b1010100 9
17
#102400
07
#102800
b1010101 9
b10000001 :
17
#103200
07
#103600
b10000010 :
b1010110 9
17
#104000
07
#104400
b1010111 9
b10000011 :
17
#104800
07
#105200
b10000100 :
b1011000 9
17
#105600
07
#106000
b1011001 9
b10000101 :
17
#106400
07
#106800
b10000110 :
b1011010 9
17
#107200
07
#107600
b1011011 9
b10000111 :
17
#108000
07
#108400
b10001000 :
b1011100 9
17
#108800
07
#109200
b1011101 9
b10001001 :
17
#109600
07
#110000
b10001010 :
b1011110 9
17
#110400
07
#110800
b1011111 9
b10001011 :
17
#111200
07
#111600
b10001100 :
b1100000 9
17
#112000
07
#112400
b1100001 9
b10001101 :
17
#112800
07
#113200
b10001110 :
b1100010 9
17
#113600
07
#114000
b1100011 9
b10001111 :
17
#114400
07
#114800
b10010000 :
b1100100 9
17
#115200
07
#115600
b1100101 9
b10010001 :
17
#116000
07
#116400
b10010010 :
b1100110 9
17
#116800
07
#117200
b1100111 9
b10010011 :
17
#117600
07
#118000
b10010100 :
b1101000 9
17
#118400
07
#118800
b1101001 9
b10010101 :
17
#119200
07
#119600
b10010110 :
b1101010 9
17
#120000
07
#120400
b1101011 9
b10010111 :
17
#120800
07
#121200
b10011000 :
b1101100 9
17
#121600
07
#122000
b1101101 9
b10011001 :
17
#122400
07
#122800
b10011010 :
b1101110 9
17
#123200
07
#123600
b1101111 9
b10011011 :
17
#124000
07
#124400
b10011100 :
b1110000 9
17
#124800
07
#125200
b1110001 9
b10011101 :
17
#125600
07
#126000
b10011110 :
b1110010 9
17
#126400
07
#126800
b1110011 9
b10011111 :
17
#127200
07
#127600
b10100000 :
b1110100 9
17
#128000
07
#128400
b1110101 9
b10100001 :
17
#128800
07
#129200
b10100010 :
b1110110 9
17
#129600
07
#130000
b1110111 9
b10100011 :
17
#130400
07
#130800
b10100100 :
b1111000 9
17
#131200
07
#131600
b1111001 9
b10100101 :
17
#132000
07
#132400
b10100110 :
b1111010 9
17
#132800
07
#133200
b1111011 9
b10100111 :
17
#133600
07
#134000
b10101000 :
b1111100 9
17
#134400
07
#134800
b1111101 9
b10101001 :
17
#135200
07
#135600
b10101010 :
b1111110 9
17
#136000
07
#136400
b1111111 9
b10101011 :
17
#136800
07
#137200
b10101100 :
b10000000 9
17
#137600
07
#138000
b10000001 9
b10101101 :
17
#138400
07
#138800
b10101110 :
b10000010 9
17
#139200
07
#139600
b10000011 9
b10101111 :
17
#140000
07
#140400
b10110000 :
b10000100 9
17
#140800
07
#141200
b10000101 9
b10110001 :
17
#141600
07
#142000
b10110010 :
b10000110 9
17
#142400
07
#142800
b10000111 9
b10110011 :
17
#143200
07
#143600
b10110100 :
b10001000 9
17
#144000
07
#144400
b10001001 9
b10110101 :
17
#144800
07
#145200
b10110110 :
b10001010 9
17
#145600
07
#146000
b10001011 9
b10110111 :
17
#146400
07
#146800
b10111000 :
b10001100 9
17
#147200
07
#147600
b10001101 9
b10111001 :
17
#148000
07
#148400
b10111010 :
b10001110 9
17
#148800
07
#149200
b10001111 9
b10111011 :
17
#149600
07
#150000
b10111100 :
b10010000 9
17
#150400
07
#150800
b10010001 9
b10111101 :
17
#151200
07
